{"type": "FeatureCollection", "id": "http://www.wikidata.org/entity/Q2542762", "name": "Wallersee", "features": [{"type": "Feature", "id": "http://data.archaeology.link/data/spphaefen/24", "name": "", "dateprops": ["begin", "end"], "properties": {"http://purl.org/cerif/frapo/isOutputOf": ["https://gepris.dfg.de/gepris/projekt/198801704"], "http://purl.org/dc/elements/1.1/created": ["2016"], "http://purl.org/dc/elements/1.1/creator": ["http://data.archaeology.link/data/spphaefen/l_kroeger"], "http://purl.org/dc/terms/isReferencedBy": ["http://data.archaeology.link/data/spphaefen/bib_Hirte_1987_Archaologie", "http://data.archaeology.link/data/spphaefen/bib_Pohl_2009_Einbaumfunde"], "http://purl.org/dc/terms/partOf": ["http://data.archaeology.link/data/spphaefen/bib_dbt_mods_00035241"], "http://rdfs.org/ns/void#inDataset": ["http://data.archaeology.link/data/spphaefen/spp_dataset"], "http://www.opengis.net/ont/geosparql#hasGeometry": ["http://data.archaeology.link/data/spphaefen/24_geom"], "http://www.spp-haefen.de/ont#locationSecure": ["highly reliable"], "http://www.spp-haefen.de/ont#place_technique": ["http://www.wikidata.org/entity/Q596073"], "http://www.w3.org/1999/02/22-rdf-syntax-ns#type": ["http://www.spp-haefen.de/ont#Harbour"], "http://www.w3.org/2000/01/rdf-schema#label": ["Wallersee"], "http://www.w3.org/2004/02/skos/core#note": ["Werner 1973", "Werner 1973, S. 44; Pohl 2009, S. 74ff.; Hirte 1987, S. 362"], "http://www.w3.org/2006/time#hasTime": ["http://data.archaeology.link/data/spphaefen/24_foundation"], "http://www.wikidata.org/prop/direct/P17": ["http://www.wikidata.org/entity/Q40"], "http://www.wikidata.org/prop/direct/P206": ["http://www.wikidata.org/entity/Q2542762"], "begin": ""}, "geometry": {"type": "Point", "coordinates": [13.171, 47.921]}}], "numberMatched": 1, "numberReturned": 1, "bbox": [13.171, 47.921, 13.171, 47.921], "crs": "http://www.opengis.net/def/crs/EPSG/0/4326"}