{"type": "FeatureCollection", "id": "http://www.wikidata.org/entity/Q2464737", "name": "Plateliai-See", "features": [{"type": "Feature", "id": "http://data.archaeology.link/data/spphaefen/2769", "name": "", "dateprops": ["begin", "end"], "properties": {"http://purl.org/cerif/frapo/isOutputOf": ["https://gepris.dfg.de/gepris/projekt/198801704"], "http://purl.org/dc/elements/1.1/created": ["2017"], "http://purl.org/dc/elements/1.1/creator": ["http://data.archaeology.link/data/spphaefen/l_kroeger"], "http://purl.org/dc/terms/partOf": ["http://data.archaeology.link/data/spphaefen/bib_dbt_mods_00035241"], "http://rdfs.org/ns/void#inDataset": ["http://data.archaeology.link/data/spphaefen/spp_dataset"], "http://www.opengis.net/ont/geosparql#hasGeometry": ["http://data.archaeology.link/data/spphaefen/2769_geom"], "http://www.spp-haefen.de/ont#locationSecure": ["highly reliable"], "http://www.spp-haefen.de/ont#place_technique": ["http://www.wikidata.org/entity/Q596073"], "http://www.w3.org/1999/02/22-rdf-syntax-ns#type": ["http://www.spp-haefen.de/ont#Harbour"], "http://www.w3.org/2000/01/rdf-schema#label": ["Plateliai 1"], "http://www.w3.org/2004/02/skos/core#note": ["Kola/\u017dulkus 2010", "Kola/\u017dulkus 2010, 157; Perminas 2008; \u017dulkus 1999", "Perminas 2008", "\u017dulkus 1999"], "http://www.w3.org/2006/time#hasTime": ["http://data.archaeology.link/data/spphaefen/2769_foundation"], "http://www.wikidata.org/prop/direct/P17": ["http://www.wikidata.org/entity/Q37"], "http://www.wikidata.org/prop/direct/P206": ["http://www.wikidata.org/entity/Q2464737"], "begin": ""}, "geometry": {"type": "Point", "coordinates": [21.842, 56.042]}}, {"type": "Feature", "id": "http://data.archaeology.link/data/spphaefen/2771", "name": "", "dateprops": ["begin", "end"], "properties": {"http://purl.org/cerif/frapo/isOutputOf": ["https://gepris.dfg.de/gepris/projekt/198801704"], "http://purl.org/dc/elements/1.1/created": ["2017"], "http://purl.org/dc/elements/1.1/creator": ["http://data.archaeology.link/data/spphaefen/l_kroeger"], "http://purl.org/dc/terms/partOf": ["http://data.archaeology.link/data/spphaefen/bib_dbt_mods_00035241"], "http://rdfs.org/ns/void#inDataset": ["http://data.archaeology.link/data/spphaefen/spp_dataset"], "http://www.opengis.net/ont/geosparql#hasGeometry": ["http://data.archaeology.link/data/spphaefen/2771_geom"], "http://www.spp-haefen.de/ont#locationSecure": ["highly reliable"], "http://www.spp-haefen.de/ont#place_technique": ["http://www.wikidata.org/entity/Q596073"], "http://www.w3.org/1999/02/22-rdf-syntax-ns#type": ["http://www.spp-haefen.de/ont#Harbour"], "http://www.w3.org/2000/01/rdf-schema#label": ["Plateliai 3"], "http://www.w3.org/2004/02/skos/core#note": ["Perminas 2008", "Perminas 2008; \u017dulkus 1999", "\u017dulkus 1999"], "http://www.w3.org/2006/time#hasTime": ["http://data.archaeology.link/data/spphaefen/2771_foundation"], "http://www.wikidata.org/prop/direct/P17": ["http://www.wikidata.org/entity/Q37"], "http://www.wikidata.org/prop/direct/P206": ["http://www.wikidata.org/entity/Q2464737"], "begin": ""}, "geometry": {"type": "Point", "coordinates": [21.845, 56.043]}}, {"type": "Feature", "id": "http://data.archaeology.link/data/spphaefen/2770", "name": "", "dateprops": ["begin", "end"], "properties": {"http://purl.org/cerif/frapo/isOutputOf": ["https://gepris.dfg.de/gepris/projekt/198801704"], "http://purl.org/dc/elements/1.1/created": ["2017"], "http://purl.org/dc/elements/1.1/creator": ["http://data.archaeology.link/data/spphaefen/l_kroeger"], "http://purl.org/dc/terms/partOf": ["http://data.archaeology.link/data/spphaefen/bib_dbt_mods_00035241"], "http://rdfs.org/ns/void#inDataset": ["http://data.archaeology.link/data/spphaefen/spp_dataset"], "http://www.opengis.net/ont/geosparql#hasGeometry": ["http://data.archaeology.link/data/spphaefen/2770_geom"], "http://www.spp-haefen.de/ont#locationSecure": ["highly reliable"], "http://www.spp-haefen.de/ont#place_technique": ["http://www.wikidata.org/entity/Q596073"], "http://www.w3.org/1999/02/22-rdf-syntax-ns#type": ["http://www.spp-haefen.de/ont#Harbour"], "http://www.w3.org/2000/01/rdf-schema#label": ["Plateliai 2"], "http://www.w3.org/2004/02/skos/core#note": ["Perminas 2008", "Perminas 2008; \u017dulkus 1999", "\u017dulkus 1999"], "http://www.w3.org/2006/time#hasTime": ["http://data.archaeology.link/data/spphaefen/2770_foundation"], "http://www.wikidata.org/prop/direct/P17": ["http://www.wikidata.org/entity/Q37"], "http://www.wikidata.org/prop/direct/P206": ["http://www.wikidata.org/entity/Q2464737"], "begin": ""}, "geometry": {"type": "Point", "coordinates": [21.84, 56.043]}}], "numberMatched": 3, "numberReturned": 3, "bbox": [21.84, 56.042, 21.845, 56.043], "crs": "http://www.opengis.net/def/crs/EPSG/0/4326"}