{"type": "FeatureCollection", "id": "http://www.wikidata.org/entity/Q36856", "name": "Zwin", "features": [{"type": "Feature", "id": "http://data.archaeology.link/data/spphaefen/40", "name": "", "dateprops": ["begin", "end"], "properties": {"http://purl.org/cerif/frapo/isOutputOf": ["https://gepris.dfg.de/gepris/projekt/198801704"], "http://purl.org/dc/elements/1.1/created": ["2015"], "http://purl.org/dc/elements/1.1/creator": ["L. Kr\u00f6ger/M. Foucher"], "http://purl.org/dc/terms/isReferencedBy": ["http://data.archaeology.link/data/spphaefen/bib_Ellmers_1972_Fruhmittelalterliche"], "http://purl.org/dc/terms/partOf": ["http://data.archaeology.link/data/spphaefen/bib_dbt_mods_00035241"], "http://rdfs.org/ns/void#inDataset": ["http://data.archaeology.link/data/spphaefen/spp_dataset"], "http://www.opengis.net/ont/geosparql#hasGeometry": ["http://data.archaeology.link/data/spphaefen/40_geom"], "http://www.spp-haefen.de/ont#locationSecure": ["uncertain"], "http://www.spp-haefen.de/ont#place_technique": ["unknown"], "http://www.w3.org/1999/02/22-rdf-syntax-ns#type": ["http://www.spp-haefen.de/ont#Harbour"], "http://www.w3.org/2000/01/rdf-schema#label": ["Br\u00fcgge, Port-de-mer"], "http://www.w3.org/2004/02/skos/core#note": ["Demerre u.a. 2009", "Ellmers 1972, S. 289f.; Demerre u.a. 2009; Marsden 1976", "Marsden 1976"], "http://www.w3.org/2006/time#hasTime": ["http://data.archaeology.link/data/spphaefen/40_foundation"], "http://www.wikidata.org/prop/direct/P17": ["http://www.wikidata.org/entity/Q31"], "http://www.wikidata.org/prop/direct/P206": ["http://www.wikidata.org/entity/Q36856"], "begin": ""}, "geometry": {"type": "Point", "coordinates": [3.222, 51.231]}}], "numberMatched": 1, "numberReturned": 1, "bbox": [3.222, 51.231, 3.222, 51.231], "crs": "http://www.opengis.net/def/crs/EPSG/0/4326"}