{"type": "FeatureCollection", "id": "http://www.wikidata.org/entity/Q2074865", "name": "River Roe", "features": [{"type": "Feature", "id": "http://data.archaeology.link/data/spphaefen/400", "name": "", "dateprops": [], "properties": {"http://purl.org/cerif/frapo/isOutputOf": ["https://gepris.dfg.de/gepris/projekt/198801704"], "http://purl.org/dc/elements/1.1/created": ["2017"], "http://purl.org/dc/elements/1.1/creator": ["http://data.archaeology.link/data/spphaefen/l_kroeger"], "http://purl.org/dc/terms/isReferencedBy": ["http://data.archaeology.link/data/spphaefen/bib_Fry_2000_Coiti", "http://data.archaeology.link/data/spphaefen/bib_Gregory_1997_Comparative"], "http://purl.org/dc/terms/partOf": ["http://data.archaeology.link/data/spphaefen/bib_dbt_mods_00035241"], "http://rdfs.org/ns/void#inDataset": ["http://data.archaeology.link/data/spphaefen/spp_dataset"], "http://www.opengis.net/ont/geosparql#hasGeometry": ["http://data.archaeology.link/data/spphaefen/400_geom"], "http://www.spp-haefen.de/ont#locationSecure": ["reliable"], "http://www.spp-haefen.de/ont#place_technique": ["http://www.wikidata.org/entity/Q596073"], "http://www.w3.org/1999/02/22-rdf-syntax-ns#type": ["http://www.spp-haefen.de/ont#Harbour"], "http://www.w3.org/2000/01/rdf-schema#label": ["River Roe, Bellarena Townland, near Limavady (Fry No. 42; Gregory I043))"], "http://www.w3.org/2004/02/skos/core#note": ["Fry 2000, 73; Gregory 1997, 295f."], "http://www.wikidata.org/prop/direct/P17": ["http://www.wikidata.org/entity/Q26"], "http://www.wikidata.org/prop/direct/P206": ["http://www.wikidata.org/entity/Q2074865"], "begin": ""}, "geometry": {"type": "Point", "coordinates": [-6.96, 55.111]}}], "numberMatched": 1, "numberReturned": 1, "bbox": [-6.96, 55.111, -6.96, 55.111], "crs": "http://www.opengis.net/def/crs/EPSG/0/4326"}