{"type": "FeatureCollection", "id": "http://www.wikidata.org/entity/Q576704", "name": "Lac d'Annecy", "features": [{"type": "Feature", "id": "http://data.archaeology.link/data/spphaefen/1314", "name": "", "dateprops": ["begin", "end"], "properties": {"http://purl.org/cerif/frapo/isOutputOf": ["https://gepris.dfg.de/gepris/projekt/198801704"], "http://purl.org/dc/elements/1.1/created": ["2016"], "http://purl.org/dc/elements/1.1/creator": ["http://data.archaeology.link/data/spphaefen/l_kroeger"], "http://purl.org/dc/terms/isReferencedBy": ["http://data.archaeology.link/data/spphaefen/bib_Hirte_1987_Archaologie", "http://data.archaeology.link/data/spphaefen/bib_Lanting_1998_Dates"], "http://purl.org/dc/terms/partOf": ["http://data.archaeology.link/data/spphaefen/bib_dbt_mods_00035241"], "http://rdfs.org/ns/void#inDataset": ["http://data.archaeology.link/data/spphaefen/spp_dataset"], "http://www.opengis.net/ont/geosparql#hasGeometry": ["http://data.archaeology.link/data/spphaefen/1314_geom"], "http://www.spp-haefen.de/ont#locationSecure": ["uncertain"], "http://www.spp-haefen.de/ont#place_technique": ["http://www.wikidata.org/entity/Q596073"], "http://www.w3.org/1999/02/22-rdf-syntax-ns#type": ["http://www.spp-haefen.de/ont#Harbour"], "http://www.w3.org/2000/01/rdf-schema#label": ["Sevrier"], "http://www.w3.org/2004/02/skos/core#note": ["Hirte 1987, S. 404f.; Lanting 1998, S. 637"], "http://www.w3.org/2006/time#hasTime": ["http://data.archaeology.link/data/spphaefen/1314_foundation"], "http://www.wikidata.org/prop/direct/P17": ["http://www.wikidata.org/entity/Q142"], "http://www.wikidata.org/prop/direct/P206": ["http://www.wikidata.org/entity/Q576704"], "begin": ""}, "geometry": {"type": "Point", "coordinates": [6.153, 45.864]}}, {"type": "Feature", "id": "http://data.archaeology.link/data/spphaefen/1057", "name": "", "dateprops": ["begin", "end"], "properties": {"http://purl.org/cerif/frapo/isOutputOf": ["https://gepris.dfg.de/gepris/projekt/198801704"], "http://purl.org/dc/elements/1.1/created": ["2014"], "http://purl.org/dc/elements/1.1/creator": ["http://data.archaeology.link/data/spphaefen/l_kroeger"], "http://purl.org/dc/terms/partOf": ["http://data.archaeology.link/data/spphaefen/bib_dbt_mods_00035241"], "http://rdfs.org/ns/void#inDataset": ["http://data.archaeology.link/data/spphaefen/spp_dataset"], "http://www.opengis.net/ont/geosparql#hasGeometry": ["http://data.archaeology.link/data/spphaefen/1057_geom"], "http://www.spp-haefen.de/ont#locationSecure": ["reliable"], "http://www.spp-haefen.de/ont#place_technique": ["http://www.wikidata.org/entity/Q5457690"], "http://www.w3.org/1999/02/22-rdf-syntax-ns#type": ["http://www.spp-haefen.de/ont#Harbour"], "http://www.w3.org/2000/01/rdf-schema#label": ["Doussard/Bredannaz"], "http://www.w3.org/2004/02/skos/core#note": ["Billaud/Rieth 2006"], "http://www.w3.org/2006/time#hasTime": ["http://data.archaeology.link/data/spphaefen/1057_foundation"], "http://www.wikidata.org/prop/direct/P17": ["http://www.wikidata.org/entity/Q142"], "http://www.wikidata.org/prop/direct/P206": ["http://www.wikidata.org/entity/Q576704"], "begin": ""}, "geometry": {"type": "Point", "coordinates": [6.209, 45.816]}}, {"type": "Feature", "id": "http://data.archaeology.link/data/spphaefen/975", "name": "", "dateprops": [], "properties": {"http://purl.org/cerif/frapo/isOutputOf": ["https://gepris.dfg.de/gepris/projekt/198801704"], "http://purl.org/dc/elements/1.1/created": ["2017"], "http://purl.org/dc/elements/1.1/creator": ["http://data.archaeology.link/data/spphaefen/l_kroeger"], "http://purl.org/dc/terms/isReferencedBy": ["http://data.archaeology.link/data/spphaefen/bib_Cordier_1972_Pirogues"], "http://purl.org/dc/terms/partOf": ["http://data.archaeology.link/data/spphaefen/bib_dbt_mods_00035241"], "http://rdfs.org/ns/void#inDataset": ["http://data.archaeology.link/data/spphaefen/spp_dataset"], "http://www.opengis.net/ont/geosparql#hasGeometry": ["http://data.archaeology.link/data/spphaefen/975_geom"], "http://www.spp-haefen.de/ont#locationSecure": ["reliable"], "http://www.spp-haefen.de/ont#place_technique": ["http://www.wikidata.org/entity/Q596073"], "http://www.w3.org/1999/02/22-rdf-syntax-ns#type": ["http://www.spp-haefen.de/ont#Harbour"], "http://www.w3.org/2000/01/rdf-schema#label": ["Annecy"], "http://www.w3.org/2004/02/skos/core#note": ["Cordier 1972, 206f."], "http://www.wikidata.org/prop/direct/P17": ["http://www.wikidata.org/entity/Q142"], "http://www.wikidata.org/prop/direct/P206": ["http://www.wikidata.org/entity/Q576704"], "begin": ""}, "geometry": {"type": "Point", "coordinates": [6.167, 45.864]}}], "numberMatched": 3, "numberReturned": 3, "bbox": [6.153, 45.816, 6.209, 45.864], "crs": "http://www.opengis.net/def/crs/EPSG/0/4326"}