{"type": "FeatureCollection", "id": "http://www.wikidata.org/entity/Q1225928", "name": "S\u00e8vre Niortaise", "features": [{"type": "Feature", "id": "http://data.archaeology.link/data/spphaefen/1153", "name": "", "dateprops": [], "properties": {"http://purl.org/cerif/frapo/isOutputOf": ["https://gepris.dfg.de/gepris/projekt/198801704"], "http://purl.org/dc/elements/1.1/created": ["2017"], "http://purl.org/dc/elements/1.1/creator": ["http://data.archaeology.link/data/spphaefen/l_kroeger"], "http://purl.org/dc/terms/isReferencedBy": ["http://data.archaeology.link/data/spphaefen/bib_Cordier_1963_Quelques"], "http://purl.org/dc/terms/partOf": ["http://data.archaeology.link/data/spphaefen/bib_dbt_mods_00035241"], "http://rdfs.org/ns/void#inDataset": ["http://data.archaeology.link/data/spphaefen/spp_dataset"], "http://www.opengis.net/ont/geosparql#hasGeometry": ["http://data.archaeology.link/data/spphaefen/1153_geom"], "http://www.spp-haefen.de/ont#locationSecure": ["reliable"], "http://www.spp-haefen.de/ont#place_technique": ["http://www.wikidata.org/entity/Q596073"], "http://www.w3.org/1999/02/22-rdf-syntax-ns#type": ["http://www.spp-haefen.de/ont#Harbour"], "http://www.w3.org/2000/01/rdf-schema#label": ["Niort 1, 1868"], "http://www.w3.org/2004/02/skos/core#note": ["Cordier 1963, 310"], "http://www.wikidata.org/prop/direct/P17": ["http://www.wikidata.org/entity/Q142"], "http://www.wikidata.org/prop/direct/P206": ["http://www.wikidata.org/entity/Q1225928"], "begin": ""}, "geometry": {"type": "Point", "coordinates": [-0.466, 46.325]}}, {"type": "Feature", "id": "http://data.archaeology.link/data/spphaefen/1154", "name": "", "dateprops": [], "properties": {"http://purl.org/cerif/frapo/isOutputOf": ["https://gepris.dfg.de/gepris/projekt/198801704"], "http://purl.org/dc/elements/1.1/created": ["2017"], "http://purl.org/dc/elements/1.1/creator": ["http://data.archaeology.link/data/spphaefen/l_kroeger"], "http://purl.org/dc/terms/isReferencedBy": ["http://data.archaeology.link/data/spphaefen/bib_Cordier_1963_Quelques"], "http://purl.org/dc/terms/partOf": ["http://data.archaeology.link/data/spphaefen/bib_dbt_mods_00035241"], "http://rdfs.org/ns/void#inDataset": ["http://data.archaeology.link/data/spphaefen/spp_dataset"], "http://www.opengis.net/ont/geosparql#hasGeometry": ["http://data.archaeology.link/data/spphaefen/1154_geom"], "http://www.spp-haefen.de/ont#locationSecure": ["reliable"], "http://www.spp-haefen.de/ont#place_technique": ["http://www.wikidata.org/entity/Q596073"], "http://www.w3.org/1999/02/22-rdf-syntax-ns#type": ["http://www.spp-haefen.de/ont#Harbour"], "http://www.w3.org/2000/01/rdf-schema#label": ["Niort 2, 1868"], "http://www.w3.org/2004/02/skos/core#note": ["Cordier 1963, 310"], "http://www.wikidata.org/prop/direct/P17": ["http://www.wikidata.org/entity/Q142"], "http://www.wikidata.org/prop/direct/P206": ["http://www.wikidata.org/entity/Q1225928"], "begin": ""}, "geometry": {"type": "Point", "coordinates": [-0.463, 46.349]}}], "numberMatched": 2, "numberReturned": 2, "bbox": [-0.466, 46.325, -0.463, 46.349], "crs": "http://www.opengis.net/def/crs/EPSG/0/4326"}