{"type": "FeatureCollection", "id": "http://www.wikidata.org/entity/Q1368230", "name": "Loch Awe", "features": [{"type": "Feature", "id": "http://data.archaeology.link/data/spphaefen/436", "name": "", "dateprops": [], "properties": {"http://purl.org/cerif/frapo/isOutputOf": ["https://gepris.dfg.de/gepris/projekt/198801704"], "http://purl.org/dc/elements/1.1/created": ["2017"], "http://purl.org/dc/elements/1.1/creator": ["http://data.archaeology.link/data/spphaefen/l_kroeger"], "http://purl.org/dc/terms/partOf": ["http://data.archaeology.link/data/spphaefen/bib_dbt_mods_00035241"], "http://rdfs.org/ns/void#inDataset": ["http://data.archaeology.link/data/spphaefen/spp_dataset"], "http://www.opengis.net/ont/geosparql#hasGeometry": ["http://data.archaeology.link/data/spphaefen/436_geom"], "http://www.spp-haefen.de/ont#locationSecure": ["reliable"], "http://www.spp-haefen.de/ont#place_technique": ["http://www.wikidata.org/entity/Q596073"], "http://www.w3.org/1999/02/22-rdf-syntax-ns#type": ["http://www.spp-haefen.de/ont#Harbour"], "http://www.w3.org/2000/01/rdf-schema#label": ["Carn an Roin (Mowat No. 16)"], "http://www.w3.org/2004/02/skos/core#note": ["Mowat 1996", "Mowat 1996, 17f."], "http://www.wikidata.org/prop/direct/P17": ["http://www.wikidata.org/entity/Q22"], "http://www.wikidata.org/prop/direct/P206": ["http://www.wikidata.org/entity/Q1368230"], "begin": ""}, "geometry": {"type": "Point", "coordinates": [-5.134, 56.354]}}], "numberMatched": 1, "numberReturned": 1, "bbox": [-5.134, 56.354, -5.134, 56.354], "crs": "http://www.opengis.net/def/crs/EPSG/0/4326"}