{"type": "FeatureCollection", "id": "http://www.wikidata.org/entity/Q14309", "name": "Guadalquivir", "features": [{"type": "Feature", "id": "http://data.archaeology.link/data/spphaefen/3212", "name": "", "dateprops": [], "properties": {"http://purl.org/cerif/frapo/isOutputOf": ["https://gepris.dfg.de/gepris/projekt/198801704"], "http://purl.org/dc/elements/1.1/created": ["2016"], "http://purl.org/dc/elements/1.1/creator": ["http://data.archaeology.link/data/spphaefen/l_kroeger"], "http://purl.org/dc/terms/isReferencedBy": ["http://data.archaeology.link/data/spphaefen/bib_Alves_1988_Dugout"], "http://purl.org/dc/terms/partOf": ["http://data.archaeology.link/data/spphaefen/bib_dbt_mods_00035241"], "http://rdfs.org/ns/void#inDataset": ["http://data.archaeology.link/data/spphaefen/spp_dataset"], "http://www.opengis.net/ont/geosparql#hasGeometry": ["http://data.archaeology.link/data/spphaefen/3212_geom"], "http://www.spp-haefen.de/ont#locationSecure": ["very uncertain"], "http://www.spp-haefen.de/ont#place_technique": ["http://www.wikidata.org/entity/Q596073"], "http://www.w3.org/1999/02/22-rdf-syntax-ns#type": ["http://www.spp-haefen.de/ont#Harbour"], "http://www.w3.org/2000/01/rdf-schema#label": ["Dona\u00f1a National Park"], "http://www.w3.org/2004/02/skos/core#note": ["Alves 1988, S. 290"], "http://www.wikidata.org/prop/direct/P17": ["http://www.wikidata.org/entity/Q29"], "http://www.wikidata.org/prop/direct/P206": ["http://www.wikidata.org/entity/Q14309"], "begin": ""}, "geometry": {"type": "Point", "coordinates": [-6.327, 36.903]}}], "numberMatched": 1, "numberReturned": 1, "bbox": [-6.327, 36.903, -6.327, 36.903], "crs": "http://www.opengis.net/def/crs/EPSG/0/4326"}