{"type": "FeatureCollection", "id": "http://www.wikidata.org/entity/Q33179736", "name": "Anfora Canal", "features": [{"type": "Feature", "id": "http://data.archaeology.link/data/spphaefen/2638", "name": "", "dateprops": ["begin", "end"], "properties": {"http://purl.org/cerif/frapo/isOutputOf": ["https://gepris.dfg.de/gepris/projekt/198801704"], "http://purl.org/dc/elements/1.1/created": ["2014"], "http://purl.org/dc/elements/1.1/creator": ["http://data.archaeology.link/data/spphaefen/l_kroeger"], "http://purl.org/dc/terms/isReferencedBy": ["http://data.archaeology.link/data/spphaefen/bib_Capulli_2013_Ships"], "http://purl.org/dc/terms/partOf": ["http://data.archaeology.link/data/spphaefen/bib_dbt_mods_00035241"], "http://rdfs.org/ns/void#inDataset": ["http://data.archaeology.link/data/spphaefen/spp_dataset"], "http://www.opengis.net/ont/geosparql#hasGeometry": ["http://data.archaeology.link/data/spphaefen/2638_geom"], "http://www.spp-haefen.de/ont#locationSecure": ["uncertain"], "http://www.spp-haefen.de/ont#place_technique": ["http://www.wikidata.org/entity/Q60520969"], "http://www.w3.org/1999/02/22-rdf-syntax-ns#type": ["http://www.spp-haefen.de/ont#Harbour"], "http://www.w3.org/2000/01/rdf-schema#comment": ["The find was located in the area of an old canal."], "http://www.w3.org/2000/01/rdf-schema#label": ["Anfora canal 1"], "http://www.w3.org/2006/time#hasTime": ["http://data.archaeology.link/data/spphaefen/2638_foundation"], "http://www.wikidata.org/prop/direct/P17": ["http://www.wikidata.org/entity/Q38"], "http://www.wikidata.org/prop/direct/P206": ["http://www.wikidata.org/entity/Q33179736"], "begin": ""}, "geometry": {"type": "Point", "coordinates": [13.332, 45.764]}}, {"type": "Feature", "id": "http://data.archaeology.link/data/spphaefen/2639", "name": "", "dateprops": ["begin", "end"], "properties": {"http://purl.org/cerif/frapo/isOutputOf": ["https://gepris.dfg.de/gepris/projekt/198801704"], "http://purl.org/dc/elements/1.1/created": ["2014"], "http://purl.org/dc/elements/1.1/creator": ["http://data.archaeology.link/data/spphaefen/l_kroeger"], "http://purl.org/dc/terms/isReferencedBy": ["http://data.archaeology.link/data/spphaefen/bib_Capulli_2013_Ships"], "http://purl.org/dc/terms/partOf": ["http://data.archaeology.link/data/spphaefen/bib_dbt_mods_00035241"], "http://rdfs.org/ns/void#inDataset": ["http://data.archaeology.link/data/spphaefen/spp_dataset"], "http://www.opengis.net/ont/geosparql#hasGeometry": ["http://data.archaeology.link/data/spphaefen/2639_geom"], "http://www.spp-haefen.de/ont#locationSecure": ["uncertain"], "http://www.spp-haefen.de/ont#place_technique": ["http://www.wikidata.org/entity/Q60520969"], "http://www.w3.org/1999/02/22-rdf-syntax-ns#type": ["http://www.spp-haefen.de/ont#Harbour"], "http://www.w3.org/2000/01/rdf-schema#comment": ["The find was located in the area of an old canal."], "http://www.w3.org/2000/01/rdf-schema#label": ["Anfora canal 2"], "http://www.w3.org/2006/time#hasTime": ["http://data.archaeology.link/data/spphaefen/2639_foundation"], "http://www.wikidata.org/prop/direct/P17": ["http://www.wikidata.org/entity/Q38"], "http://www.wikidata.org/prop/direct/P206": ["http://www.wikidata.org/entity/Q33179736"], "begin": ""}, "geometry": {"type": "Point", "coordinates": [13.329, 45.763]}}], "numberMatched": 2, "numberReturned": 2, "bbox": [13.329, 45.763, 13.332, 45.764], "crs": "http://www.opengis.net/def/crs/EPSG/0/4326"}