{"type": "FeatureCollection", "id": "http://www.wikidata.org/entity/Q649696", "name": "Vend\u00e9e", "features": [{"type": "Feature", "id": "http://data.archaeology.link/data/spphaefen/1076", "name": "", "dateprops": [], "properties": {"http://purl.org/cerif/frapo/isOutputOf": ["https://gepris.dfg.de/gepris/projekt/198801704"], "http://purl.org/dc/elements/1.1/created": ["2017"], "http://purl.org/dc/elements/1.1/creator": ["http://data.archaeology.link/data/spphaefen/l_kroeger"], "http://purl.org/dc/terms/isReferencedBy": ["http://data.archaeology.link/data/spphaefen/bib_Joncheray_1986_embarcations"], "http://purl.org/dc/terms/partOf": ["http://data.archaeology.link/data/spphaefen/bib_dbt_mods_00035241"], "http://rdfs.org/ns/void#inDataset": ["http://data.archaeology.link/data/spphaefen/spp_dataset"], "http://www.opengis.net/ont/geosparql#hasGeometry": ["http://data.archaeology.link/data/spphaefen/1076_geom"], "http://www.spp-haefen.de/ont#locationSecure": ["reliable"], "http://www.spp-haefen.de/ont#place_technique": ["http://www.wikidata.org/entity/Q596073"], "http://www.w3.org/1999/02/22-rdf-syntax-ns#type": ["http://www.spp-haefen.de/ont#Harbour"], "http://www.w3.org/2000/01/rdf-schema#label": ["Fontenay-le-Comte, Bassin de Captation"], "http://www.w3.org/2004/02/skos/core#note": ["Joncheray 1986, 8f."], "http://www.wikidata.org/prop/direct/P17": ["http://www.wikidata.org/entity/Q142"], "http://www.wikidata.org/prop/direct/P206": ["http://www.wikidata.org/entity/Q649696"], "begin": ""}, "geometry": {"type": "Point", "coordinates": [-0.805, 46.466]}}], "numberMatched": 1, "numberReturned": 1, "bbox": [-0.805, 46.466, -0.805, 46.466], "crs": "http://www.opengis.net/def/crs/EPSG/0/4326"}